portfolio_management/__init__.py
portfolio_management/analysis.py
portfolio_management/backtest.py
portfolio_management/fx.py
portfolio_management/port_construction.py
portfolio_management/port_tscv.py
portfolio_management/risk.py
portfolio_management/statistics.py
portfolio_management/utils.py
tests/__init__.py
tests/conftest.py
tests/test_analysis.py
tests/test_backtest.py
tests/test_fx.py
tests/test_portfolio_construction.py
tests/test_risk.py
tests/test_statistics.py
tests/test_utils.py
portfolio_management-0.2.0.dist-info/LICENSE
portfolio_management-0.2.0.dist-info/METADATA
portfolio_management-0.2.0.dist-info/WHEEL
portfolio_management-0.2.0.dist-info/top_level.txt
portfolio_management-0.2.0.dist-info/RECORD
