Metadata-Version: 2.2
Name: portfolio_management
Version: 0.2.0
Summary: Portfolio Management Helper
Author: Fernando Rocha Urbano
Author-email: fernando.rocha.urbano@gmail.com
Classifier: Programming Language :: Python :: 3
Classifier: License :: OSI Approved :: MIT License
Classifier: Operating System :: OS Independent
Requires-Python: >=3.8
License-File: LICENSE
Requires-Dist: pandas>=2.2.3
Requires-Dist: numpy>=2.1.1
Requires-Dist: matplotlib>=3.9.2
Requires-Dist: scipy>=1.14.1
Requires-Dist: yfinance>=0.2.43
Requires-Dist: datetime>=3.0.3
Requires-Dist: statsmodels>=0.14.3
Requires-Dist: scikit-learn>=1.4.2
Requires-Dist: scikit-optimize>=0.10.2
Requires-Dist: seaborn>=0.13.2
Requires-Dist: openpyxl>=3.1.3
Requires-Dist: ipywidgets>=8.1.5
Requires-Dist: arch>=7.1.0
Requires-Dist: setuptools>=57.5.0
Requires-Dist: cvxpy>=1.6.0
Dynamic: author
Dynamic: author-email
Dynamic: classifier
Dynamic: requires-dist
Dynamic: requires-python
Dynamic: summary
